csela1/mux2x1.v
module MUX2to1_w1(output y, input i0, i1, s);

  wire e0, e1;
  not (sn, s);
  
  and (e0, i0, sn);
  and  (e1, i1, s);
  
  or (y, e0, e1);
  
endmodule

csela1/mux2x1a.v
module MUX2to1_w4(output [3:0] y, input [3:0] i0, i1, input s);

  wire [3:0] e0, e1;
  not (sn, s);
  
  and (e0[0], i0[0], sn);
  and (e0[1], i0[1], sn);
  and  (e0[2], i0[2], sn);
  and  (e0[3], i0[3], sn);
      
  and  (e1[0], i1[0], s);
  and (e1[1], i1[1], s);
  and  (e1[2], i1[2], s);
  and (e1[3], i1[3], s);
  
  or  (y[0], e0[0], e1[0]);
  or  (y[1], e0[1], e1[1]);
  or  (y[2], e0[2], e1[2]);
  or  (y[3], e0[3], e1[3]);
  
endmodule

csela1/fa.v
// Full Adder
module FA(output sum, cout, input a, b, cin);
  wire w0, w1, w2;
  
  xor (w0, a, b);
  xor (sum, w0, cin);
  
  and (w1, w0, cin);
  and (w2, a, b);
  or (cout, w1, w2);
endmodule

csela1/rca4.v
// Ripple Carry Adder with cin - 4 bits
module RCA4(output [3:0] sum, output cout, input [3:0] a, b, input cin);
  
  wire [3:1] c;
  
  FA fa0(sum[0], c[1], a[0], b[0], cin);
  FA fa[2:1](sum[2:1], c[3:2], a[2:1], b[2:1], c[2:1]);
  FA fa31(sum[3], cout, a[3], b[3], c[3]);
  
endmodule

csela1/csela.v
// Carry Select Adder - 32 bits
module CSelA32(output [31:0] sum, output cout, input [31:0] a, b);

  wire [31:0] sum0, sum1;
  wire [7:1] c;
  wire [7:0] cout0, cout1;

  RCA4 rca0_0(sum0[3:0], cout0[0], a[3:0], b[3:0], 0);
  RCA4 rca0_1(sum1[3:0], cout1[0], a[3:0], b[3:0], 1);
  MUX2to1_w4 mux0_sum(sum[3:0], sum0[3:0], sum1[3:0], 0);
  MUX2to1_w1 mux0_cout(c[1], cout0[0], cout1[0], 0);

  RCA4 rca_other_0[6:1](sum0[27:4], cout0[6:1], a[27:4], b[27:4], 1'b0);
  RCA4 rca_other_1[6:1](sum1[27:4], cout1[6:1], a[27:4], b[27:4], 1'b1);
  MUX2to1_w4 mux_other_sum[6:1](sum[27:4], sum0[27:4], sum1[27:4], c[6:1]);
  MUX2to1_w1 mux_other_cout[6:1](c[7:2], cout0[6:1], cout1[6:1], c[6:1]);

  RCA4 rca_last_0(sum0[31:28], cout0[7], a[31:28], b[31:28], 0);
  RCA4 rca_last_1(sum1[31:28], cout1[7], a[31:28], b[31:28], 1);
  MUX2to1_w4 mux_last_sum(sum[31:28], sum0[31:28], sum1[31:28], c[7]);
  MUX2to1_w1 mux_last_cout(cout, cout0[7], cout1[7], c[7]);

endmodule

csela1/tb.v
`timescale 1ns/1ns 
module test;
reg [31:0] a, b;
wire cout;
wire [31:0] sum;
integer i;
CSelA32 ins1(sum, cout,a, b);

initial begin
$dumpfile("csela.vcd");
$dumpvars(1);
 end
 
 initial
 for(i=0;i<=15;i=i+1)
 begin
 a=i;
 b=i*2;
 #5;
 end
 endmodule

csela1/csela.vcd
$date
	Wed Feb 02 12:09:25 2022
$end
$version
	Icarus Verilog
$end
$timescale
	1ns
$end
$scope module test $end
$var wire 32 ! sum [31:0] $end
$var wire 1 " cout $end
$var reg 32 # a [31:0] $end
$var reg 32 $ b [31:0] $end
$var integer 32 % i [31:0] $end
$upscope $end
$enddefinitions $end
#0
$dumpvars
b0 %
b0 $
b0 #
0"
b0 !
$end
#5
b11 !
b10 $
b1 #
b1 %
#10
b110 !
b100 $
b10 #
b10 %
#15
b1001 !
b110 $
b11 #
b11 %
#20
b1100 !
b1000 $
b100 #
b100 %
#25
b1111 !
b1010 $
b101 #
b101 %
#30
b10010 !
b1100 $
b110 #
b110 %
#35
b10101 !
b1110 $
b111 #
b111 %
#40
b11000 !
b10000 $
b1000 #
b1000 %
#45
b11011 !
b10010 $
b1001 #
b1001 %
#50
b11110 !
b10100 $
b1010 #
b1010 %
#55
b100001 !
b10110 $
b1011 #
b1011 %
#60
b100100 !
b11000 $
b1100 #
b1100 %
#65
b100111 !
b11010 $
b1101 #
b1101 %
#70
b101010 !
b11100 $
b1110 #
b1110 %
#75
b101101 !
b11110 $
b1111 #
b1111 %
#80
b10000 %
